logslacker/SlackLogHandler.py
logslacker/__init__.py
logslacker/command_line.py
logslacker-0.0.1.dev1.dist-info/DESCRIPTION.rst
logslacker-0.0.1.dev1.dist-info/METADATA
logslacker-0.0.1.dev1.dist-info/RECORD
logslacker-0.0.1.dev1.dist-info/WHEEL
logslacker-0.0.1.dev1.dist-info/entry_points.txt
logslacker-0.0.1.dev1.dist-info/metadata.json
logslacker-0.0.1.dev1.dist-info/top_level.txt
